termpyx/__init__.py
termpyx/src/abs/console.py
termpyx/src/enums/color.py
termpyx/src/obj/console.py
termpyx-0.1.0.dist-info/METADATA
termpyx-0.1.0.dist-info/WHEEL
termpyx-0.1.0.dist-info/RECORD
