Metadata-Version: 2.1
Name: termpyx
Version: 0.1.0
Summary: TermPyX is a Python library designed to enhance terminal logging with colors and animations. It provides an intuitive interface for displaying various log levels, including success, info, warning, danger, and debug messages, all with customizable colors and optional animated text output.
Author: techatlasdev
Author-email: srgoqui@gmail.com
Requires-Python: >=3.10,<4.0
Classifier: Programming Language :: Python :: 3
Classifier: Programming Language :: Python :: 3.10
Classifier: Programming Language :: Python :: 3.11
Classifier: Programming Language :: Python :: 3.12
Classifier: Programming Language :: Python :: 3.13
